{"name":"Videobrowser","tagline":"A tiny browser for videos stored on your local disc. Created especially for slow and old computers.","body":"VideoBrowser\r\n============\r\n\r\nA tiny browser for videos stored on your local disc. Created especially for slow and old computers.\r\n\r\n![Screenshot of VideoBrowser](http://www.difficultdecisions.de/wp-content/uploads/2010/06/videobrowser.png)\r\n\r\nDependencies\r\n------------\r\n\r\n* a Video-Player of your choice (Totem is used by default)\r\n* ffmpeg (for thumbnails)\r\n* python 2.6 + pygtk\r\n\r\nInstallation\r\n------------\r\n\r\nIt's not necessary to install the software. You just need to make VideoBrowser.py executable. Afterwards you can start it via\r\n\r\n    python VideoBrowser.py\r\n\r\nor\r\n\r\n    /Pfad/zu/VideoBrowser.py\r\n\r\nConfiguration\r\n-------------\r\n\r\nAt the first start a folder .VideoBrowser is create in your home directory. Thumbnails are cached and the config file is stored within this folder. The config file allows you to define values like the default video player or directories that should be used (e.g. for thumbnails).\r\n\r\nControl\r\n-------\r\n\r\nThe default controls are:\r\n\r\n* Rotate left right: cursor key left & right\r\n* Play: space\r\n* Quit: ‘q’ or ESC\r\n\r\nThe keys can be changed via the config file.\r\n","google":"","note":"Don't delete this file! It's used internally to help with page regeneration."}